django_googleauth_ng-2.5.dist-info/DESCRIPTION.rst
django_googleauth_ng-2.5.dist-info/METADATA
django_googleauth_ng-2.5.dist-info/RECORD
django_googleauth_ng-2.5.dist-info/WHEEL
django_googleauth_ng-2.5.dist-info/metadata.json
django_googleauth_ng-2.5.dist-info/top_level.txt
googleauth/__init__.py
googleauth/backends.py
googleauth/models.py
googleauth/urls.py
googleauth/views.py
