Metadata-Version: 2.0
Name: django-googleauth-ng
Version: 2.5
Summary: OAuth 2.0 authentication for Google and Google Apps accounts
Home-page: https://github.com/ojarva/django-googleauth
Author: Jeremy Carbaugh
Author-email: jcarbaugh@gmail.com
License: BSD
Platform: any
Classifier: Development Status :: 4 - Beta
Classifier: Intended Audience :: Developers
Classifier: License :: OSI Approved :: BSD License
Classifier: Natural Language :: English
Classifier: Operating System :: OS Independent
Classifier: Programming Language :: Python
Classifier: Topic :: Software Development :: Libraries :: Python Modules
Requires-Dist: PyJWT (==0.4.1)
Requires-Dist: requests (==2.5.1)
